GraKeL-0.1.10.dist-info/LICENSE
GraKeL-0.1.10.dist-info/WHEEL
GraKeL-0.1.10.dist-info/METADATA
GraKeL-0.1.10.dist-info/RECORD
GraKeL-0.1.10.dist-info/top_level.txt
grakel/graph.py
grakel/__init__.py
grakel/tools.py
grakel/graph_kernels.py
grakel/utils.py
grakel/tests/data/Cuneiform/README.txt
grakel/tests/data/Cuneiform/Cuneiform_graph_labels.txt
grakel/tests/data/Cuneiform/Cuneiform_edge_labels.txt
grakel/tests/data/Cuneiform/Cuneiform_graph_indicator.txt
grakel/tests/data/Cuneiform/Cuneiform_node_attributes.txt
grakel/tests/data/Cuneiform/Cuneiform_edge_attributes.txt
grakel/tests/data/Cuneiform/Cuneiform_node_labels.txt
grakel/tests/data/Cuneiform/Cuneiform_A.txt
grakel/tests/data/MUTAG/README.txt
grakel/tests/data/MUTAG/MUTAG_node_labels.txt
grakel/tests/data/MUTAG/MUTAG_A.txt
grakel/tests/data/MUTAG/MUTAG_graph_indicator.txt
grakel/tests/data/MUTAG/MUTAG_graph_labels.txt
grakel/tests/data/MUTAG/MUTAG_edge_labels.txt
grakel/kernels/neighborhood_hash.py
grakel/kernels/neighborhood_subgraph_pairwise_distance.py
grakel/kernels/graphlet_sampling.py
grakel/kernels/_c_functions.cpython-310-aarch64-linux-gnu.so
grakel/kernels/weisfeiler_lehman.py
grakel/kernels/multiscale_laplacian.py
grakel/kernels/svm_theta.py
grakel/kernels/__init__.py
grakel/kernels/edge_histogram.py
grakel/kernels/vertex_histogram.py
grakel/kernels/pyramid_match.py
grakel/kernels/propagation.py
grakel/kernels/hadamard_code.py
grakel/kernels/lovasz_theta.py
grakel/kernels/random_walk.py
grakel/kernels/subgraph_matching.py
grakel/kernels/kernel.py
grakel/kernels/shortest_path.py
grakel/kernels/weisfeiler_lehman_optimal_assignment.py
grakel/kernels/odd_sth.py
grakel/kernels/graph_hopper.py
grakel/kernels/core_framework.py
grakel/kernels/_c_functions/header.pxd
grakel/kernels/_c_functions/__init__.pyx
grakel/kernels/_c_functions/functions.pyx
grakel/kernels/_c_functions/src/ArashPartov.cpp
grakel/kernels/_c_functions/src/sm_core.cpp
grakel/kernels/_c_functions/include/functions.hpp
grakel/kernels/_isomorphism/intpyblissmodule_2.cc
grakel/kernels/_isomorphism/intpyblissmodule_3.cc
