Metadata-Version: 2.1
Name: GraKeL
Version: 0.1.10
Summary: A scikit-learn compatible library for graph kernels
Author-email: Ioannis-Siglidis <y.siglidis@gmail.com>
License: New BSD License
Project-URL: documentation, https://ysig.github.io/GraKeL/
Project-URL: feedback, http://www.lix.polytechnique.fr/dascim/contact/
Project-URL: source, https://github.com/ysig/GraKeL/
Project-URL: tracker, https://github.com/ysig/GraKeL/issues
Classifier: Intended Audience :: Science/Research
Classifier: Intended Audience :: Developers
Classifier: License :: OSI Approved
Classifier: Programming Language :: C
Classifier: Programming Language :: Python
Classifier: Topic :: Software Development
Classifier: Topic :: Scientific/Engineering
Classifier: Operating System :: POSIX
Classifier: Operating System :: Unix
Classifier: Operating System :: MacOS
Classifier: Programming Language :: Python :: 3
Requires-Python: >=3.5
License-File: LICENSE
Requires-Dist: numpy >=1.14.0
Requires-Dist: cython >=0.27.3
Requires-Dist: scikit-learn >=0.19
Requires-Dist: six >=1.11.0
Requires-Dist: future >=0.16.0
Requires-Dist: joblib
Provides-Extra: dev
Requires-Dist: cvxopt >=1.2.0 ; extra == 'dev'
Requires-Dist: pytest ; extra == 'dev'
Requires-Dist: pytest-coverage ; extra == 'dev'
Requires-Dist: torch-geometric ; extra == 'dev'
Provides-Extra: lovasz
Requires-Dist: cvxopt >=1.2.0 ; extra == 'lovasz'
Provides-Extra: test
Requires-Dist: pytest ; extra == 'test'
Requires-Dist: pytest-coverage ; extra == 'test'
Requires-Dist: torch-geometric ; extra == 'test'
Provides-Extra: wheel
Requires-Dist: pytest ; extra == 'wheel'
Requires-Dist: pytest-coverage ; extra == 'wheel'
